lrboost/__init__.py
lrboost/_version.py
lrboost/lrboost.py
lrboost/utils.py
lrboost/tests/__init__.py
lrboost/tests/test_common.py
lrboost/tests/test_template.py
lrboost-0.2.1.dist-info/LICENSE
lrboost-0.2.1.dist-info/METADATA
lrboost-0.2.1.dist-info/WHEEL
lrboost-0.2.1.dist-info/top_level.txt
lrboost-0.2.1.dist-info/RECORD
